priyanshu_cli/__init__.py
priyanshu_cli/main.py
priyanshu_cli-1.0.0.dist-info/METADATA
priyanshu_cli-1.0.0.dist-info/WHEEL
priyanshu_cli-1.0.0.dist-info/entry_points.txt
priyanshu_cli-1.0.0.dist-info/top_level.txt
priyanshu_cli-1.0.0.dist-info/RECORD
