Metadata-Version: 2.4
Name: priyanshu-cli
Version: 1.0.0
Summary: A simple CLI tool to fetch GitHub repositories
Author: Priyanshu Paikra
Keywords: cli github repositories python
Requires-Dist: click
Requires-Dist: requests
Dynamic: author
Dynamic: keywords
Dynamic: requires-dist
Dynamic: summary
